{
  "project_info": {
    "project_number": "291731637583",
    "project_id": "flutter-message-sample-app",
    "storage_bucket": "flutter-message-sample-app.appspot.com"
  },
  "client": [
    {
      "client_info": {
        "mobilesdk_app_id": "1:291731637583:android:06d647de289f68b0a0f13a",
        "android_client_info": {
          "package_name": "com.flutter_message_sample.app"
        }
      },
      "oauth_client": [
        {
          "client_id": "291731637583-m5j55oilrv5lauj1l7nhnnhotqi4siqc.apps.googleusercontent.com",
          "client_type": 3
        }
      ],
      "api_key": [
        {
          "current_key": "AIzaSyCG068cpjPU1tTVsquYep1m4mJw3YZxQYE"
        }
      ],
      "services": {
        "appinvite_service": {
          "other_platform_oauth_client": [
            {
              "client_id": "291731637583-m5j55oilrv5lauj1l7nhnnhotqi4siqc.apps.googleusercontent.com",
              "client_type": 3
            }
          ]
        }
      }
    }
  ],
  "configuration_version": "1"
}